synthegrator/JUnit.xsd
synthegrator/__init__.py
synthegrator/code_problem_builders.py
synthegrator/code_problems.py
synthegrator/code_solver.py
synthegrator/df_converters.py
synthegrator/environments.py
synthegrator/execution_threading.py
synthegrator/few_shotting.py
synthegrator/lm_few_shotting_tools.py
synthegrator/memory_fs.py
synthegrator/problem_rendering.py
synthegrator/problem_rendering_insertion_tags.py
synthegrator/prompt_renderer_edit.py
synthegrator/prompt_renderer_questions.py
synthegrator/prompting_test_case_selection.py
synthegrator/response_parser.py
synthegrator/sandboxing.py
synthegrator/solution_eval.py
synthegrator/toytest.py
synthegrator/transformation_spec.py
synthegrator/uncertainty_modeling.py
synthegrator/util.py
synthegrator/version.py
synthegrator/_vendor/README.md
synthegrator/_vendor/__init__.py
synthegrator/_vendor/epicbox/LICENSE
synthegrator/_vendor/epicbox/README.md
synthegrator/_vendor/epicbox/__init__.py
synthegrator/_vendor/epicbox/config.py
synthegrator/_vendor/epicbox/exceptions.py
synthegrator/_vendor/epicbox/sandboxes.py
synthegrator/_vendor/epicbox/utils.py
synthegrator/_vendor/human_eval_ref/LICENSE
synthegrator/_vendor/human_eval_ref/__init__.py
synthegrator/_vendor/human_eval_ref/evaluation.py
synthegrator/_vendor/human_eval_ref/execution.py
synthegrator/dypybench/__init__.py
synthegrator/dypybench/copy-project.sh
synthegrator/dypybench/dypybench.py.nolint
synthegrator/dypybench/run-test-temp.sh
synthegrator/human_eval/LICENSE
synthegrator/human_eval/__init__.py
synthegrator/human_eval/evaluation.py
synthegrator/human_eval/execution.py
synthegrator/lang_specs/__init__.py
synthegrator/lang_specs/lang_spec.py
synthegrator/lang_specs/lang_spec_java.py
synthegrator/lang_specs/lang_spec_python.py
synthegrator/lang_specs/lang_util.py
synthegrator/lang_specs/extra_files/DummyTest.java
synthegrator/lang_specs/extra_files/default_java_pom.xml
synthegrator/randomstuff/__init__.py
synthegrator/randomstuff/getk.py
synthegrator-0.14.1.0.dist-info/licenses/LICENSE
synthegrator-0.14.1.0.dist-info/METADATA
synthegrator-0.14.1.0.dist-info/WHEEL
synthegrator-0.14.1.0.dist-info/top_level.txt
synthegrator-0.14.1.0.dist-info/RECORD
