Metadata-Version: 2.4
Name: synthegrator
Version: 0.14.1.0
Summary: Framework for code synthesis and AI4SE research
Author: David Gros, Claudio Spiess
Project-URL: Homepage, https://github.com/DaiseyCode/synthegrator
Keywords: code synthesis,llm
Classifier: Programming Language :: Python :: 3
Requires-Python: >=3.10
License-File: LICENSE
Requires-Dist: lmwrapper[hf]<0.18,>=0.17
Requires-Dist: numpy<2.3,>=1.24.3
Requires-Dist: Pygments<3.0,>=2.15.1
Requires-Dist: tqdm<5.0,>=4.65.0
Requires-Dist: datasets<3.2,>=3.1
Requires-Dist: diskcache<6.0,>=5.6.3
Requires-Dist: libcst<2.0,>=1.0.1
Requires-Dist: tree-sitter==0.23.2
Requires-Dist: tree-sitter-language-pack==0.9.0
Requires-Dist: pytest~=8.4.1
Requires-Dist: lxml>=4.9.3
Requires-Dist: xxhash<4.0,>=3.3.0
Requires-Dist: typeguard<5.0,>=4.1
Requires-Dist: rank-bm25<0.3,>=0.2.2
Requires-Dist: docker<8,>=7.1
Requires-Dist: python-dateutil>=2.4
Requires-Dist: requests>=2.14.2
Requires-Dist: structlog>=15.3
Provides-Extra: dev
Requires-Dist: ruff>=0.2.2; extra == "dev"
Requires-Dist: pytest-cov~=4.1.0; extra == "dev"
Dynamic: license-file
